tidevice/__init__.py
tidevice/__main__.py
tidevice/_compat.py
tidevice/_crash.py
tidevice/_device.py
tidevice/_hexdump.py
tidevice/_imagemounter.py
tidevice/_installation.py
tidevice/_instruments.py
tidevice/_ipautil.py
tidevice/_perf.py
tidevice/_proto.py
tidevice/_relay.py
tidevice/_safe_socket.py
tidevice/_ssl.py
tidevice/_sync.py
tidevice/_types.py
tidevice/_usbmux.py
tidevice/_utils.py
tidevice/_version.py
tidevice/_wdaproxy.py
tidevice/bplist.py
tidevice/exceptions.py
tidevice/plistlib2.py
tidevice/requests_usbmux.py
tidevice/struct2.py
glority_tidevice-0.4.0.dist-info/AUTHORS
glority_tidevice-0.4.0.dist-info/LICENSE
glority_tidevice-0.4.0.dist-info/METADATA
glority_tidevice-0.4.0.dist-info/WHEEL
glority_tidevice-0.4.0.dist-info/entry_points.txt
glority_tidevice-0.4.0.dist-info/pbr.json
glority_tidevice-0.4.0.dist-info/top_level.txt
glority_tidevice-0.4.0.dist-info/RECORD
