Metadata-Version: 2.1
Name: glority-tidevice
Version: 0.4.0
Summary: UNKNOWN
Home-page: UNKNOWN
License: MIT
Platform: UNKNOWN
Classifier: Environment :: Console
Classifier: Operating System :: POSIX
Classifier: Programming Language :: Python :: 3
Classifier: Topic :: Software Development :: Libraries :: Python Modules
Classifier: Topic :: Software Development :: Testing
Requires-Python: >=3.6
Requires-Dist: Pillow
Requires-Dist: requests
Requires-Dist: colored
Requires-Dist: packaging
Requires-Dist: tornado
Requires-Dist: simple-tornado (>=0.2.2)
Requires-Dist: retry
Requires-Dist: simplejson
Requires-Dist: tabulate
Requires-Dist: logzero
Requires-Dist: loguru
Requires-Dist: deprecation
Provides-Extra: openssl
Requires-Dist: pyOpenSSL ; extra == 'openssl'
Requires-Dist: pyasn1 ; extra == 'openssl'
